fiver/__init__.py
fiver/__main__.py
fiver/client.py
fiver/server.py
fiver/utils.py
fiver/version.py
fiver-0.0.1.dist-info/LICENSE
fiver-0.0.1.dist-info/METADATA
fiver-0.0.1.dist-info/WHEEL
fiver-0.0.1.dist-info/entry_points.txt
fiver-0.0.1.dist-info/top_level.txt
fiver-0.0.1.dist-info/RECORD
