Metadata-Version: 2.1
Name: fiver
Version: 0.0.1
Summary: A simple monitor linux
Author-email: Min <minha05112003a@gmail.com>
Project-URL: Homepage, https://github.com/min-awm/fiver
Project-URL: Issues, https://github.com/min-awm/fiver/issues
Classifier: Programming Language :: Python :: 3
Classifier: License :: OSI Approved :: MIT License
Classifier: Operating System :: OS Independent
Requires-Python: >=3.12
License-File: LICENSE
Requires-Dist: questionary==2.0.1
Requires-Dist: python-daemon==3.0.1
Requires-Dist: pickleDB==0.9.2
Requires-Dist: textual==0.76.0
Requires-Dist: psutil==6.0.0
